tweettr/__init__.py
tweettr/_base.py
tweettr/_emoji.py
tweettr/_objects.py
tweettr/_version.py
tweettr-0.1.0.dist-info/LICENSE.md
tweettr-0.1.0.dist-info/METADATA
tweettr-0.1.0.dist-info/WHEEL
tweettr-0.1.0.dist-info/top_level.txt
tweettr-0.1.0.dist-info/RECORD
