Metadata-Version: 2.1
Name: tweettr
Version: 0.1.0
Summary: tweettr is a `attrdict` like wrapper around (a few) Twitter JSON objects.
Home-page: https://github.com/ap--/tweettr
Author: Andreas Poehlmann
Author-email: andreas@poehlmann.io
License: MIT
Platform: UNKNOWN
Classifier: Programming Language :: Python :: 3.8
Requires-Python: >=3.8
